xrea/__init__.py
xrea/api.py
xrea/error.py
xrea/service.py
xrea-0.1.1.dist-info/DESCRIPTION.rst
xrea-0.1.1.dist-info/METADATA
xrea-0.1.1.dist-info/RECORD
xrea-0.1.1.dist-info/WHEEL
xrea-0.1.1.dist-info/metadata.json
xrea-0.1.1.dist-info/top_level.txt
