Metadata-Version: 2.0
Name: xrea
Version: 0.1.1
Summary: XREA API wrapper
Home-page: https://github.com/tpdn/xrea
Author: NAKAMORI Ryosuke
Author-email: me@tpdn.kim
License: BSD-2-Clause
Keywords: xrea coreserver
Platform: UNKNOWN
Classifier: Programming Language :: Python
Classifier: Programming Language :: Python :: 3
Classifier: Programming Language :: Python :: 3.4
Classifier: Programming Language :: Python :: 3.5
Classifier: Programming Language :: Python :: 3.6
Classifier: License :: OSI Approved :: BSD License
Classifier: Development Status :: 4 - Beta
Classifier: Intended Audience :: Developers
Requires-Python: >=3.4
Requires-Dist: requests
